redditwallpapers
