Metadata-Version: 1.0
Name: redditwallpapers
Version: 1.6
Summary: Automatically sets the top trending, good resolution images on reddit as your wallpaper.
Home-page: https://github.com/yask123/redditwallpapers
Author: Yask Srivastava
Author-email: yask123@gmail.com
License: MIT
Platform: UNKNOWN
